d7leadfinder/__init__.py
d7leadfinder/d7_lead_finder_api.py
d7leadfinder/utils.py
d7_lf_api_geopopos-1.0.2.dist-info/LICENSE
d7_lf_api_geopopos-1.0.2.dist-info/METADATA
d7_lf_api_geopopos-1.0.2.dist-info/WHEEL
d7_lf_api_geopopos-1.0.2.dist-info/top_level.txt
d7_lf_api_geopopos-1.0.2.dist-info/RECORD
