Metadata-Version: 2.1
Name: d7-lf-api-geopopos
Version: 1.0.2
Summary: A pythonic api wrapper for the D7 Lead Finder API
Home-page: https://github.com/geopopos/d7leadfinderapi
Author: Georgios Roros
Author-email: george.roros25@gmail.com
License: UNKNOWN
Platform: UNKNOWN
Classifier: Programming Language :: Python :: 3
Classifier: License :: OSI Approved :: MIT License
Classifier: Operating System :: OS Independent
Requires-Python: >=3.6
Requires-Dist: requests
